[{"name":"start_processing.action_controller","payload":{"controller":"EventsController","action":"index","params":{"action":"index","controller":"events"},"format":"html","method":"GET","path":"/events"},"time":"2013-03-23T15:35:39-04:00","transaction_id":"50ba99936622fb15b370","end":"2013-03-23T15:35:39-04:00","duration":0.004},{"name":"sql.active_record","payload":{"sql":"SELECT \"events\".* FROM \"events\" ","name":"Event Load","connection_id":70339380917480,"binds":[]},"time":"2013-03-23T15:35:39-04:00","transaction_id":"50ba99936622fb15b370","end":"2013-03-23T15:35:39-04:00","duration":0.18000000000000002},{"name":"!render_template.action_view","payload":{"virtual_path":"events/index"},"time":"2013-03-23T15:35:39-04:00","transaction_id":"50ba99936622fb15b370","end":"2013-03-23T15:35:39-04:00","duration":1.79},{"name":"render_template.action_view","payload":{"identifier":"/Users/alex/Documents/college/spring13/272/phase_3/app/views/events/index.html.erb","layout":"layouts/application"},"time":"2013-03-23T15:35:39-04:00","transaction_id":"50ba99936622fb15b370","end":"2013-03-23T15:35:39-04:00","duration":1.818},{"name":"!render_template.action_view","payload":{"virtual_path":"layouts/application"},"time":"2013-03-23T15:35:39-04:00","transaction_id":"50ba99936622fb15b370","end":"2013-03-23T15:35:39-04:00","duration":53.385000000000005},{"name":"process_action.action_controller","payload":{"controller":"EventsController","action":"index","params":{"action":"index","controller":"events"},"format":"html","method":"GET","path":"/events","status":200,"view_runtime":56.671,"db_runtime":0.18000000000000002},"time":"2013-03-23T15:35:39-04:00","transaction_id":"50ba99936622fb15b370","end":"2013-03-23T15:35:39-04:00","duration":57.889}]