[{"name":"start_processing.action_controller","payload":{"controller":"EventsController","action":"show","params":{"action":"show","controller":"events","id":"1"},"format":"html","method":"GET","path":"/events/1"},"time":"2013-03-20T23:44:01-04:00","transaction_id":"d464b1223f994afbb128","end":"2013-03-20T23:44:01-04:00","duration":0.004},{"name":"sql.active_record","payload":{"sql":"SELECT  \"events\".* FROM \"events\"  WHERE \"events\".\"id\" = ? LIMIT 1","name":"Event Load","connection_id":70145238699880,"binds":[[{"name":"id","sql_type":"INTEGER","null":false,"limit":null,"precision":null,"scale":null,"type":"integer","default":null,"primary":true,"coder":null},"1"]]},"time":"2013-03-20T23:44:01-04:00","transaction_id":"d464b1223f994afbb128","end":"2013-03-20T23:44:01-04:00","duration":0.125},{"name":"!render_template.action_view","payload":{"virtual_path":"events/show","exception":["NameError","undefined local variable or method `event' for #<#<Class:0x007f97ea5ee4d8>:0x007f97ec123f50>"]},"time":"2013-03-20T23:44:01-04:00","transaction_id":"d464b1223f994afbb128","end":"2013-03-20T23:44:01-04:00","duration":5.047000000000001},{"name":"render_template.action_view","payload":{"identifier":"/Users/alex/Documents/college/spring13/272/phase_3/app/views/events/show.html.erb","layout":"layouts/application","exception":["ActionView::Template::Error","undefined local variable or method `event' for #<#<Class:0x007f97ea5ee4d8>:0x007f97ec123f50>"]},"time":"2013-03-20T23:44:01-04:00","transaction_id":"d464b1223f994afbb128","end":"2013-03-20T23:44:01-04:00","duration":9.129},{"name":"process_action.action_controller","payload":{"controller":"EventsController","action":"show","params":{"action":"show","controller":"events","id":"1"},"format":"html","method":"GET","path":"/events/1","exception":["ActionView::Template::Error","undefined local variable or method `event' for #<#<Class:0x007f97ea5ee4d8>:0x007f97ec123f50>"],"status":"500"},"time":"2013-03-20T23:44:01-04:00","transaction_id":"d464b1223f994afbb128","end":"2013-03-20T23:44:01-04:00","duration":11.634},{"name":"process_action.action_controller.exception","payload":{"call":"ActionView::Template::Error (undefined local variable or method `event' for #<#<Class:0x007f97ea5ee4d8>:0x007f97ec123f50>)"},"time":0,"transaction_id":null,"end":0,"duration":0.0},{"name":"process_action.action_controller.exception","payload":{"call":"app/views/events/show.html.erb:10:in `_app_views_events_show_html_erb__479352830647925206_70145220820480'"},"time":0,"transaction_id":null,"end":0,"duration":0.0}]