[{"name":"start_processing.action_controller","payload":{"controller":"StudentsController","action":"show","params":{"action":"show","controller":"students","id":"206"},"format":"html","method":"GET","path":"/students/206"},"time":"2013-03-27T10:45:09-04:00","transaction_id":"7402ef323f9b6187477e","end":"2013-03-27T10:45:09-04:00","duration":0.002},{"name":"sql.active_record","payload":{"sql":"SELECT  \"students\".* FROM \"students\"  WHERE \"students\".\"id\" = ? LIMIT 1","name":"Student Load","connection_id":70294841069800,"binds":[[{"name":"id","sql_type":"INTEGER","null":false,"limit":null,"precision":null,"scale":null,"type":"integer","default":null,"primary":true,"coder":null},"206"]]},"time":"2013-03-27T10:45:09-04:00","transaction_id":"7402ef323f9b6187477e","end":"2013-03-27T10:45:09-04:00","duration":0.14200000000000002},{"name":"sql.active_record","payload":{"sql":"SELECT \"sections\".* FROM \"sections\" INNER JOIN \"registrations\" ON \"sections\".\"id\" = \"registrations\".\"section_id\" WHERE \"registrations\".\"student_id\" = 206","name":"Section Load","connection_id":70294841069800,"binds":[]},"time":"2013-03-27T10:45:09-04:00","transaction_id":"7402ef323f9b6187477e","end":"2013-03-27T10:45:09-04:00","duration":0.322},{"name":"sql.active_record","payload":{"sql":"SELECT  \"events\".* FROM \"events\"  WHERE \"events\".\"id\" = 2 LIMIT 1","name":"Event Load","connection_id":70294841069800,"binds":[]},"time":"2013-03-27T10:45:09-04:00","transaction_id":"7402ef323f9b6187477e","end":"2013-03-27T10:45:09-04:00","duration":0.088},{"name":"sql.active_record","payload":{"sql":"SELECT  \"events\".* FROM \"events\"  WHERE \"events\".\"id\" = 1 LIMIT 1","name":"Event Load","connection_id":70294841069800,"binds":[]},"time":"2013-03-27T10:45:09-04:00","transaction_id":"7402ef323f9b6187477e","end":"2013-03-27T10:45:09-04:00","duration":0.102},{"name":"sql.active_record","payload":{"sql":"SELECT  \"events\".* FROM \"events\"  WHERE \"events\".\"id\" = 3 LIMIT 1","name":"Event Load","connection_id":70294841069800,"binds":[]},"time":"2013-03-27T10:45:09-04:00","transaction_id":"7402ef323f9b6187477e","end":"2013-03-27T10:45:09-04:00","duration":0.108},{"name":"!render_template.action_view","payload":{"virtual_path":"students/show"},"time":"2013-03-27T10:45:09-04:00","transaction_id":"7402ef323f9b6187477e","end":"2013-03-27T10:45:09-04:00","duration":6.622},{"name":"render_template.action_view","payload":{"identifier":"/Users/alex/Documents/college/spring13/272/phase_3/app/views/students/show.html.erb","layout":"layouts/application"},"time":"2013-03-27T10:45:09-04:00","transaction_id":"7402ef323f9b6187477e","end":"2013-03-27T10:45:09-04:00","duration":6.652},{"name":"!render_template.action_view","payload":{"virtual_path":"partials/_footer"},"time":"2013-03-27T10:45:09-04:00","transaction_id":"7402ef323f9b6187477e","end":"2013-03-27T10:45:09-04:00","duration":0.443},{"name":"render_partial.action_view","payload":{"identifier":"/Users/alex/Documents/college/spring13/272/phase_3/app/views/partials/_footer.html.erb"},"time":"2013-03-27T10:45:09-04:00","transaction_id":"7402ef323f9b6187477e","end":"2013-03-27T10:45:09-04:00","duration":0.48700000000000004},{"name":"!render_template.action_view","payload":{"virtual_path":"layouts/application"},"time":"2013-03-27T10:45:09-04:00","transaction_id":"7402ef323f9b6187477e","end":"2013-03-27T10:45:09-04:00","duration":25.363},{"name":"process_action.action_controller","payload":{"controller":"StudentsController","action":"show","params":{"action":"show","controller":"students","id":"206"},"format":"html","method":"GET","path":"/students/206","status":200,"view_runtime":33.293,"db_runtime":0.762},"time":"2013-03-27T10:45:09-04:00","transaction_id":"7402ef323f9b6187477e","end":"2013-03-27T10:45:09-04:00","duration":35.067}]