[{"name":"start_processing.action_controller","payload":{"controller":"EventsController","action":"index","params":{"action":"index","controller":"events"},"format":"html","method":"GET","path":"/events"},"time":"2013-03-29T21:28:30-04:00","transaction_id":"b3899b30750ca9a45c4d","end":"2013-03-29T21:28:30-04:00","duration":0.003},{"name":"sql.active_record","payload":{"sql":"SELECT \"events\".* FROM \"events\" ","name":"Event Load","connection_id":70110567369620,"binds":[]},"time":"2013-03-29T21:28:30-04:00","transaction_id":"b3899b30750ca9a45c4d","end":"2013-03-29T21:28:30-04:00","duration":0.257},{"name":"!render_template.action_view","payload":{"virtual_path":"events/index"},"time":"2013-03-29T21:28:30-04:00","transaction_id":"b3899b30750ca9a45c4d","end":"2013-03-29T21:28:30-04:00","duration":1.59},{"name":"render_template.action_view","payload":{"identifier":"/Users/alex/Documents/college/spring13/272/phase_3/app/views/events/index.html.erb","layout":"layouts/application"},"time":"2013-03-29T21:28:30-04:00","transaction_id":"b3899b30750ca9a45c4d","end":"2013-03-29T21:28:30-04:00","duration":1.618},{"name":"!render_template.action_view","payload":{"virtual_path":"partials/_footer"},"time":"2013-03-29T21:28:30-04:00","transaction_id":"b3899b30750ca9a45c4d","end":"2013-03-29T21:28:30-04:00","duration":0.491},{"name":"render_partial.action_view","payload":{"identifier":"/Users/alex/Documents/college/spring13/272/phase_3/app/views/partials/_footer.html.erb"},"time":"2013-03-29T21:28:30-04:00","transaction_id":"b3899b30750ca9a45c4d","end":"2013-03-29T21:28:30-04:00","duration":0.5379999999999999},{"name":"!render_template.action_view","payload":{"virtual_path":"layouts/application"},"time":"2013-03-29T21:28:30-04:00","transaction_id":"b3899b30750ca9a45c4d","end":"2013-03-29T21:28:30-04:00","duration":25.956},{"name":"process_action.action_controller","payload":{"controller":"EventsController","action":"index","params":{"action":"index","controller":"events"},"format":"html","method":"GET","path":"/events","status":200,"view_runtime":29.145999999999997,"db_runtime":0.257},"time":"2013-03-29T21:28:30-04:00","transaction_id":"b3899b30750ca9a45c4d","end":"2013-03-29T21:28:30-04:00","duration":30.959}]