[{"name":"start_processing.action_controller","payload":{"controller":"StudentsController","action":"index","params":{"action":"index","controller":"students"},"format":"html","method":"GET","path":"/students"},"time":"2013-03-29T15:51:04-04:00","transaction_id":"7e74bbe107e044aa90ea","end":"2013-03-29T15:51:04-04:00","duration":0.002},{"name":"sql.active_record","payload":{"sql":"SELECT  \"students\".* FROM \"students\"  WHERE (students.active = 't') ORDER BY last_name, first_name LIMIT 10 OFFSET 0","name":"Student Load","connection_id":70318320992740,"binds":[]},"time":"2013-03-29T15:51:04-04:00","transaction_id":"7e74bbe107e044aa90ea","end":"2013-03-29T15:51:04-04:00","duration":0.944},{"name":"sql.active_record","payload":{"sql":"SELECT COUNT(*) FROM \"students\"  WHERE (students.active = 't')","name":null,"connection_id":70318320992740,"binds":[]},"time":"2013-03-29T15:51:04-04:00","transaction_id":"7e74bbe107e044aa90ea","end":"2013-03-29T15:51:04-04:00","duration":0.16799999999999998},{"name":"sql.active_record","payload":{"sql":"SELECT COUNT(*) FROM \"students\" ","name":null,"connection_id":70318320992740,"binds":[]},"time":"2013-03-29T15:51:04-04:00","transaction_id":"7e74bbe107e044aa90ea","end":"2013-03-29T15:51:04-04:00","duration":0.12000000000000001},{"name":"sql.active_record","payload":{"sql":"SELECT  \"students\".* FROM \"students\"  WHERE (students.active = 'f') ORDER BY last_name, first_name LIMIT 10 OFFSET 0","name":"Student Load","connection_id":70318320992740,"binds":[]},"time":"2013-03-29T15:51:04-04:00","transaction_id":"7e74bbe107e044aa90ea","end":"2013-03-29T15:51:04-04:00","duration":0.266},{"name":"!render_template.action_view","payload":{"virtual_path":"students/index"},"time":"2013-03-29T15:51:04-04:00","transaction_id":"7e74bbe107e044aa90ea","end":"2013-03-29T15:51:04-04:00","duration":9.323},{"name":"render_template.action_view","payload":{"identifier":"/Users/alex/Documents/college/spring13/272/phase_3/app/views/students/index.html.erb","layout":"layouts/application"},"time":"2013-03-29T15:51:04-04:00","transaction_id":"7e74bbe107e044aa90ea","end":"2013-03-29T15:51:04-04:00","duration":9.346},{"name":"!render_template.action_view","payload":{"virtual_path":"partials/_footer"},"time":"2013-03-29T15:51:04-04:00","transaction_id":"7e74bbe107e044aa90ea","end":"2013-03-29T15:51:04-04:00","duration":0.428},{"name":"render_partial.action_view","payload":{"identifier":"/Users/alex/Documents/college/spring13/272/phase_3/app/views/partials/_footer.html.erb"},"time":"2013-03-29T15:51:04-04:00","transaction_id":"7e74bbe107e044aa90ea","end":"2013-03-29T15:51:04-04:00","duration":0.47300000000000003},{"name":"!render_template.action_view","payload":{"virtual_path":"layouts/application"},"time":"2013-03-29T15:51:04-04:00","transaction_id":"7e74bbe107e044aa90ea","end":"2013-03-29T15:51:04-04:00","duration":24.809},{"name":"process_action.action_controller","payload":{"controller":"StudentsController","action":"index","params":{"action":"index","controller":"students"},"format":"html","method":"GET","path":"/students","status":200,"view_runtime":35.171,"db_runtime":1.498},"time":"2013-03-29T15:51:04-04:00","transaction_id":"7e74bbe107e044aa90ea","end":"2013-03-29T15:51:04-04:00","duration":37.346}]