[{"name":"start_processing.action_controller","payload":{"controller":"StudentsController","action":"index","params":{"action":"index","controller":"students"},"format":"html","method":"GET","path":"/students"},"time":"2013-03-29T21:28:23-04:00","transaction_id":"b3899b30750ca9a45c4d","end":"2013-03-29T21:28:23-04:00","duration":0.004},{"name":"sql.active_record","payload":{"sql":"SELECT  \"students\".* FROM \"students\"  WHERE (students.active = 't') ORDER BY last_name, first_name LIMIT 10 OFFSET 0","name":"Student Load","connection_id":70110567369620,"binds":[]},"time":"2013-03-29T21:28:23-04:00","transaction_id":"b3899b30750ca9a45c4d","end":"2013-03-29T21:28:23-04:00","duration":1.189},{"name":"sql.active_record","payload":{"sql":"SELECT COUNT(*) FROM \"students\"  WHERE (students.active = 't')","name":null,"connection_id":70110567369620,"binds":[]},"time":"2013-03-29T21:28:23-04:00","transaction_id":"b3899b30750ca9a45c4d","end":"2013-03-29T21:28:23-04:00","duration":0.188},{"name":"sql.active_record","payload":{"sql":"SELECT COUNT(*) FROM \"students\" ","name":null,"connection_id":70110567369620,"binds":[]},"time":"2013-03-29T21:28:23-04:00","transaction_id":"b3899b30750ca9a45c4d","end":"2013-03-29T21:28:23-04:00","duration":0.101},{"name":"sql.active_record","payload":{"sql":"SELECT  \"students\".* FROM \"students\"  WHERE (students.active = 'f') ORDER BY last_name, first_name LIMIT 10 OFFSET 0","name":"Student Load","connection_id":70110567369620,"binds":[]},"time":"2013-03-29T21:28:23-04:00","transaction_id":"b3899b30750ca9a45c4d","end":"2013-03-29T21:28:23-04:00","duration":0.30200000000000005},{"name":"!render_template.action_view","payload":{"virtual_path":"students/index"},"time":"2013-03-29T21:28:23-04:00","transaction_id":"b3899b30750ca9a45c4d","end":"2013-03-29T21:28:23-04:00","duration":10.66},{"name":"render_template.action_view","payload":{"identifier":"/Users/alex/Documents/college/spring13/272/phase_3/app/views/students/index.html.erb","layout":"layouts/application"},"time":"2013-03-29T21:28:23-04:00","transaction_id":"b3899b30750ca9a45c4d","end":"2013-03-29T21:28:23-04:00","duration":10.683},{"name":"!render_template.action_view","payload":{"virtual_path":"partials/_footer"},"time":"2013-03-29T21:28:23-04:00","transaction_id":"b3899b30750ca9a45c4d","end":"2013-03-29T21:28:23-04:00","duration":0.435},{"name":"render_partial.action_view","payload":{"identifier":"/Users/alex/Documents/college/spring13/272/phase_3/app/views/partials/_footer.html.erb"},"time":"2013-03-29T21:28:23-04:00","transaction_id":"b3899b30750ca9a45c4d","end":"2013-03-29T21:28:23-04:00","duration":0.483},{"name":"!render_template.action_view","payload":{"virtual_path":"layouts/application"},"time":"2013-03-29T21:28:23-04:00","transaction_id":"b3899b30750ca9a45c4d","end":"2013-03-29T21:28:23-04:00","duration":25.122},{"name":"process_action.action_controller","payload":{"controller":"StudentsController","action":"index","params":{"action":"index","controller":"students"},"format":"html","method":"GET","path":"/students","status":200,"view_runtime":35.887,"db_runtime":1.78},"time":"2013-03-29T21:28:23-04:00","transaction_id":"b3899b30750ca9a45c4d","end":"2013-03-29T21:28:23-04:00","duration":38.352}]