[{"name":"start_processing.action_controller","payload":{"controller":"SectionsController","action":"show","params":{"action":"show","controller":"sections","id":"3"},"format":"html","method":"GET","path":"/sections/3"},"time":"2013-03-29T15:32:08-04:00","transaction_id":"7e74bbe107e044aa90ea","end":"2013-03-29T15:32:08-04:00","duration":0.003},{"name":"sql.active_record","payload":{"sql":"SELECT  \"sections\".* FROM \"sections\"  WHERE \"sections\".\"id\" = ? LIMIT 1","name":"Section Load","connection_id":70318300557280,"binds":[[{"name":"id","sql_type":"INTEGER","null":false,"limit":null,"precision":null,"scale":null,"type":"integer","default":null,"primary":true,"coder":null},"3"]]},"time":"2013-03-29T15:32:08-04:00","transaction_id":"7e74bbe107e044aa90ea","end":"2013-03-29T15:32:08-04:00","duration":0.232},{"name":"sql.active_record","payload":{"sql":"SELECT  \"events\".* FROM \"events\"  WHERE \"events\".\"id\" = 3 LIMIT 1","name":"Event Load","connection_id":70318300557280,"binds":[]},"time":"2013-03-29T15:32:08-04:00","transaction_id":"7e74bbe107e044aa90ea","end":"2013-03-29T15:32:08-04:00","duration":0.12999999999999998},{"name":"sql.active_record","payload":{"sql":"SELECT \"students\".* FROM \"students\" INNER JOIN \"registrations\" ON \"students\".\"id\" = \"registrations\".\"student_id\" WHERE \"registrations\".\"section_id\" = 3","name":"Student Load","connection_id":70318300557280,"binds":[]},"time":"2013-03-29T15:32:08-04:00","transaction_id":"7e74bbe107e044aa90ea","end":"2013-03-29T15:32:08-04:00","duration":0.2},{"name":"!render_template.action_view","payload":{"virtual_path":"sections/show"},"time":"2013-03-29T15:32:08-04:00","transaction_id":"7e74bbe107e044aa90ea","end":"2013-03-29T15:32:08-04:00","duration":2.979},{"name":"render_template.action_view","payload":{"identifier":"/Users/alex/Documents/college/spring13/272/phase_3/app/views/sections/show.html.erb","layout":"layouts/application"},"time":"2013-03-29T15:32:08-04:00","transaction_id":"7e74bbe107e044aa90ea","end":"2013-03-29T15:32:08-04:00","duration":3.005},{"name":"!render_template.action_view","payload":{"virtual_path":"partials/_footer"},"time":"2013-03-29T15:32:08-04:00","transaction_id":"7e74bbe107e044aa90ea","end":"2013-03-29T15:32:08-04:00","duration":0.412},{"name":"render_partial.action_view","payload":{"identifier":"/Users/alex/Documents/college/spring13/272/phase_3/app/views/partials/_footer.html.erb"},"time":"2013-03-29T15:32:08-04:00","transaction_id":"7e74bbe107e044aa90ea","end":"2013-03-29T15:32:08-04:00","duration":0.449},{"name":"!render_template.action_view","payload":{"virtual_path":"layouts/application"},"time":"2013-03-29T15:32:08-04:00","transaction_id":"7e74bbe107e044aa90ea","end":"2013-03-29T15:32:08-04:00","duration":24.891},{"name":"process_action.action_controller","payload":{"controller":"SectionsController","action":"show","params":{"action":"show","controller":"sections","id":"3"},"format":"html","method":"GET","path":"/sections/3","status":200,"view_runtime":29.141000000000002,"db_runtime":0.5619999999999999},"time":"2013-03-29T15:32:08-04:00","transaction_id":"7e74bbe107e044aa90ea","end":"2013-03-29T15:32:08-04:00","duration":31.104}]