[{"name":"start_processing.action_controller","payload":{"controller":"HomeController","action":"contact","params":{"action":"contact","controller":"home"},"format":"html","method":"GET","path":"/contact"},"time":"2013-03-29T18:39:35-04:00","transaction_id":"9f3ac97c8eb719d8ab47","end":"2013-03-29T18:39:35-04:00","duration":0.002},{"name":"!render_template.action_view","payload":{"virtual_path":"home/contact"},"time":"2013-03-29T18:39:35-04:00","transaction_id":"9f3ac97c8eb719d8ab47","end":"2013-03-29T18:39:35-04:00","duration":1.101},{"name":"render_template.action_view","payload":{"identifier":"/Users/alex/Documents/college/spring13/272/phase_3/app/views/home/contact.html.erb","layout":"layouts/application"},"time":"2013-03-29T18:39:35-04:00","transaction_id":"9f3ac97c8eb719d8ab47","end":"2013-03-29T18:39:35-04:00","duration":1.142},{"name":"!render_template.action_view","payload":{"virtual_path":"partials/_footer"},"time":"2013-03-29T18:39:35-04:00","transaction_id":"9f3ac97c8eb719d8ab47","end":"2013-03-29T18:39:35-04:00","duration":0.433},{"name":"render_partial.action_view","payload":{"identifier":"/Users/alex/Documents/college/spring13/272/phase_3/app/views/partials/_footer.html.erb"},"time":"2013-03-29T18:39:35-04:00","transaction_id":"9f3ac97c8eb719d8ab47","end":"2013-03-29T18:39:35-04:00","duration":0.46799999999999997},{"name":"!render_template.action_view","payload":{"virtual_path":"layouts/application"},"time":"2013-03-29T18:39:35-04:00","transaction_id":"9f3ac97c8eb719d8ab47","end":"2013-03-29T18:39:35-04:00","duration":25.138},{"name":"process_action.action_controller","payload":{"controller":"HomeController","action":"contact","params":{"action":"contact","controller":"home"},"format":"html","method":"GET","path":"/contact","status":200,"view_runtime":27.685000000000002,"db_runtime":0},"time":"2013-03-29T18:39:35-04:00","transaction_id":"9f3ac97c8eb719d8ab47","end":"2013-03-29T18:39:35-04:00","duration":28.015}]